yoruba_tts/__init__.py
yoruba_tts/cli.py
yoruba_tts/core.py
yoruba_tts/models/__init__.py
yoruba_tts/models/model_manager.py
yoruba_tts/utils/__init__.py
yoruba_tts/utils/audio_utils.py
yoruba_tts-0.1.0.dist-info/licenses/LICENSE
yoruba_tts-0.1.0.dist-info/METADATA
yoruba_tts-0.1.0.dist-info/WHEEL
yoruba_tts-0.1.0.dist-info/entry_points.txt
yoruba_tts-0.1.0.dist-info/top_level.txt
yoruba_tts-0.1.0.dist-info/RECORD
