Metadata-Version: 2.4
Name: yoruba-tts
Version: 0.1.0
Summary: Yoruba Text-to-Speech package - downloads models automatically
Author: Your Name
Author-email: your.email@example.com
Requires-Python: >=3.7
License-File: LICENSE
Requires-Dist: torch>=1.9.0
Requires-Dist: transformers>=4.20.0
Requires-Dist: numpy>=1.21.0
Requires-Dist: scipy>=1.7.0
Requires-Dist: soundfile>=0.10.0
Dynamic: author
Dynamic: author-email
Dynamic: description
Dynamic: description-content-type
Dynamic: license-file
Dynamic: requires-dist
Dynamic: requires-python
Dynamic: summary
